rest_social_auth/__init__.py
rest_social_auth/serializers.py
rest_social_auth/strategy.py
rest_social_auth/urls_jwt_pair.py
rest_social_auth/urls_jwt_sliding.py
rest_social_auth/urls_knox.py
rest_social_auth/urls_session.py
rest_social_auth/urls_token.py
rest_social_auth/views.py
rest_social_auth-9.0.0.dist-info/licenses/LICENSE
rest_social_auth-9.0.0.dist-info/METADATA
rest_social_auth-9.0.0.dist-info/WHEEL
rest_social_auth-9.0.0.dist-info/top_level.txt
rest_social_auth-9.0.0.dist-info/RECORD
