Metadata-Version: 2.4
Name: rest_social_auth
Version: 9.0.0
Summary: Django rest framework resources for social auth
Home-page: https://github.com/st4lk/django-rest-social-auth
Author: st4lk
Author-email: alexevseev@gmail.com
License: MIT license
Keywords: django,social,auth,rest,login,signin,signup,oauth
Platform: Any
Classifier: Environment :: Web Environment
Classifier: Framework :: Django
Classifier: Intended Audience :: Developers
Classifier: License :: OSI Approved :: MIT License
Classifier: Operating System :: OS Independent
Classifier: Programming Language :: Python
Classifier: Programming Language :: Python :: 3.7
Classifier: Programming Language :: Python :: 3.8
Classifier: Programming Language :: Python :: 3.9
Classifier: Programming Language :: Python :: 3.10
Classifier: Programming Language :: Python :: 3.11
Classifier: Topic :: Utilities
License-File: LICENSE
Requires-Dist: django>=4.2
Requires-Dist: djangorestframework<4.0
Requires-Dist: social-auth-core<5.0,>=4.6.1
Requires-Dist: social-auth-app-django<6.0,>=5.4.3
Dynamic: author
Dynamic: author-email
Dynamic: classifier
Dynamic: description
Dynamic: description-content-type
Dynamic: home-page
Dynamic: keywords
Dynamic: license
Dynamic: license-file
Dynamic: platform
Dynamic: requires-dist
Dynamic: summary
